dssdk/__init__.py
dssdk/api_client.py
dssdk-0.0.1.dist-info/LICENSE
dssdk-0.0.1.dist-info/METADATA
dssdk-0.0.1.dist-info/WHEEL
dssdk-0.0.1.dist-info/top_level.txt
dssdk-0.0.1.dist-info/RECORD
