Metadata-Version: 2.1
Name: dssdk
Version: 0.0.1
Summary: sdk for dataset system
Home-page: https://pypi.org/project/dssdk/
Author: zhangping
Author-email: teleping@gmail.com
Project-URL: Bug Tracker, https://pypi.org/project/dssdk/
Classifier: Programming Language :: Python :: 3
Classifier: License :: OSI Approved :: MIT License
Classifier: Operating System :: OS Independent
Requires-Python: >=3.7
License-File: LICENSE
Requires-Dist: numpy
Requires-Dist: pandas
Requires-Dist: requests
